pyspark_pi/__init__.py
pyspark_pi/auth.py
pyspark_pi/context.py
pyspark_pi/data_source.py
pyspark_pi/errors.py
pyspark_pi/helpers.py
pyspark_pi/input_partition.py
pyspark_pi/reader.py
pyspark_pi/ds_options/__init__.py
pyspark_pi/ds_options/config.py
pyspark_pi/ds_options/params.py
pyspark_pi/ds_options/shared.py
pyspark_pi/pi/__init__.py
pyspark_pi/pi/api.py
pyspark_pi/pi/path.py
pyspark_pi/pi/point.py
pyspark_pi/pi/time.py
pyspark_pi-0.3.0.dist-info/licenses/LICENSE
pyspark_pi-0.3.0.dist-info/METADATA
pyspark_pi-0.3.0.dist-info/WHEEL
pyspark_pi-0.3.0.dist-info/top_level.txt
pyspark_pi-0.3.0.dist-info/RECORD
