Metadata-Version: 2.4
Name: pyspark-pi
Version: 0.3.0
Summary: A custom Spark data source for connecting to Aveva's Pi Web API.
Author: William Simpson
Project-URL: Homepage, https://github.com/william-c-simpson/pyspark-pi
Requires-Python: >=3.11
License-File: LICENSE
Requires-Dist: requests==2.32.4
Provides-Extra: kerberos
Requires-Dist: requests-kerberos==0.15.0; extra == "kerberos"
Provides-Extra: dev
Requires-Dist: pytest==8.4.1; extra == "dev"
Requires-Dist: twine==6.1.0; extra == "dev"
Requires-Dist: build==1.2.2.post1; extra == "dev"
Dynamic: license-file
